pyafl_qemu_trace/__init__.py
pyafl_qemu_trace/binaries/__init__.py
pyafl_qemu_trace/binaries/afl-qemu-trace-aarch64
pyafl_qemu_trace/binaries/afl-qemu-trace-x86_64
pyafl_qemu_trace/events/__init__.py
pyafl_qemu_trace/events/events.py
pyafl_qemu_trace/parse/__init__.py
pyafl_qemu_trace/parse/parse.py
pyafl_qemu_trace/parse/regs.py
pyafl_qemu_trace/run/__init__.py
pyafl_qemu_trace/run/run.py
pyafl_qemu_trace-0.3.3.dist-info/WHEEL
pyafl_qemu_trace-0.3.3.dist-info/METADATA
pyafl_qemu_trace-0.3.3.dist-info/RECORD
