Metadata-Version: 2.1
Name: pyafl-qemu-trace
Version: 0.3.3
Summary: A pip-installable distribution of afl-qemu-trace.
Home-page: https://github.com/novafacing/pyafl_qemu_trace.git
Author: novafacing
Author-email: rowanbhart@gmail.com
Requires-Python: >=3.8,<4.0
Classifier: Programming Language :: Python :: 3
Classifier: Programming Language :: Python :: 3.10
Classifier: Programming Language :: Python :: 3.8
Classifier: Programming Language :: Python :: 3.9
Requires-Dist: attrs (>=21.4.0,<22.0.0)
Project-URL: Repository, https://github.com/novafacing/pyafl_qemu_trace.git
